mdapi/__init__.py
mdapi/confdata/__init__.py
mdapi/confdata/servlogr.py
mdapi/confdata/standard.py
mdapi/database/__init__.py
mdapi/database/base.py
mdapi/database/main.py
mdapi/database/sqlq.py
mdapi/main.py
mdapi/services/__init__.py
mdapi/services/apimodel.py
mdapi/services/appviews.py
mdapi/services/homepage.html
mdapi/services/main.py
mdapi-3.1.7.dist-info/LICENSE
mdapi-3.1.7.dist-info/METADATA
mdapi-3.1.7.dist-info/WHEEL
mdapi-3.1.7.dist-info/entry_points.txt
mdapi-3.1.7.dist-info/RECORD
