Metadata-Version: 2.3
Name: mdapi
Version: 3.1.7
Summary: A simple API for serving the metadata from the RPM repositories
License: GPL-3.0-or-later
Keywords: rpm,centos,fedora,metadata,repositories
Author: Akashdeep Dhar
Author-email: akashdeep.dhar@gmail.com
Maintainer: Akashdeep Dhar
Maintainer-email: akashdeep.dhar@gmail.com
Requires-Python: >=3.8,<4.0
Classifier: Development Status :: 4 - Beta
Classifier: Environment :: Web Environment
Classifier: Framework :: AsyncIO
Classifier: Framework :: aiohttp
Classifier: Intended Audience :: System Administrators
Classifier: License :: OSI Approved :: GNU General Public License v3 or later (GPLv3+)
Classifier: Natural Language :: English
Classifier: Operating System :: POSIX :: Linux
Classifier: Programming Language :: Python :: 3
Classifier: Programming Language :: Python :: 3.8
Classifier: Programming Language :: Python :: 3.9
Classifier: Programming Language :: Python :: 3.10
Classifier: Programming Language :: Python :: 3.11
Classifier: Programming Language :: Python :: 3.12
Classifier: Programming Language :: Python :: 3.13
Classifier: Topic :: Database
Classifier: Topic :: Internet :: WWW/HTTP :: WSGI :: Application
Classifier: Topic :: Software Development
Classifier: Topic :: System :: Archiving :: Packaging
Classifier: Topic :: System :: Operating System
Requires-Dist: aiohttp (>=3.8.1,<4.0.0)
Requires-Dist: aiosqlite (>=0.18.0,<0.22.0)
Requires-Dist: click (>=8.1.3,<9.0.0)
Requires-Dist: fedora-messaging (>=3.0.2,<4.0.0)
Requires-Dist: gunicorn (>=20.1.0,<24.0.0)
Requires-Dist: mdapi-messages (>=1.0.0,<2.0.0)
Requires-Dist: pyzstd (>=0.15.0,<0.17.0)
Requires-Dist: requests (>=2.28.1,<3.0.0)
Requires-Dist: setuptools
Requires-Dist: uvloop (>=0.17.0,<0.22.0)
Project-URL: Documentation, https://github.com/fedora-infra/mdapi/blob/develop/README.md
Project-URL: Homepage, https://github.com/fedora-infra/mdapi
Project-URL: Repository, https://github.com/fedora-infra/mdapi
